{
  "id": 4,
  "categoryTitle": "رابطه با دوستان و همسالان",
  "required": true,
  "minSelection": 1,
  "maxSelection": 3,
  "description": "لطفاً 1 تا 3 مورد از موارد زیر را انتخاب کنید",
  "questions": [
    {
      "id": 15,
      "text": "مشکل در دوست یابی",
      "category": "رابطه با دوستان"
    },
    {
      "id": 16,
      "text": "روابطم با دیگران متشنج است",
      "category": "رابطه با دوستان"
    },
    {
      "id": 17,
      "text": "تصویر ذهنی نامناسبی از خود دارم",
      "category": "رابطه با دوستان"
    },
    {
      "id": 18,
      "text": "احساس پوچی می‌کنم",
      "category": "رابطه با دوستان"
    }
  ]
}